billing_datatrans/__init__.py
billing_datatrans/actions.py
billing_datatrans/admin.py
billing_datatrans/apps.py
billing_datatrans/datatrans_psp.py
billing_datatrans/models.py
billing_datatrans/urls.py
billing_datatrans/views.py
billing_datatrans/migrations/0001_initial.py
billing_datatrans/migrations/__init__.py
billing_datatrans/signals/__init__.py
billing_datatrans/signals/handlers.py
django_customer_billing_datatrans-1.0.5.dist-info/LICENSE
django_customer_billing_datatrans-1.0.5.dist-info/METADATA
django_customer_billing_datatrans-1.0.5.dist-info/WHEEL
django_customer_billing_datatrans-1.0.5.dist-info/top_level.txt
django_customer_billing_datatrans-1.0.5.dist-info/RECORD
