Metadata-Version: 2.1
Name: django-customer-billing-datatrans
Version: 1.0.5
Summary: UNKNOWN
Home-page: https://github.com/skioo/django-customer-billing-datatrans
Author: Nicholas Wolff
Author-email: nwolff@gmail.com
License: MIT
Download-URL: https://pypi.python.org/pypi/django-customer-billing-datatrans
Platform: UNKNOWN
Classifier: Development Status :: 5 - Production/Stable
Classifier: Environment :: Web Environment
Classifier: Framework :: Django :: 2.0
Classifier: Framework :: Django :: 2.1
Classifier: Framework :: Django :: 2.2
Classifier: Framework :: Django :: 3.1
Classifier: Intended Audience :: Developers
Classifier: License :: OSI Approved :: MIT License
Classifier: Operating System :: OS Independent
Classifier: Programming Language :: Python
Classifier: Programming Language :: Python :: 3.6
Classifier: Programming Language :: Python :: 3.7
Classifier: Programming Language :: Python :: 3.8
Requires-Dist: Django (>=2.0)
Requires-Dist: djangorestframework
Requires-Dist: django-money
Requires-Dist: structlog
Requires-Dist: hashids
Requires-Dist: typing
Requires-Dist: django-customer-billing (>=1.7.2)
Requires-Dist: django-datatrans-gateway
